beast/__init__.py
beast/decoder.py
beast/encoder.py
beast/server.py
beast/types.py
mode_s/__init__.py
mode_s/adsb.py
mode_s/cpr.py
mode_s/crc.py
mode_s/misc.py
mode_s/modulator.py
bestie-0.0.0rc1.dist-info/METADATA
bestie-0.0.0rc1.dist-info/WHEEL
bestie-0.0.0rc1.dist-info/top_level.txt
bestie-0.0.0rc1.dist-info/RECORD
