Metadata-Version: 2.4
Name: bestie
Version: 0.0.0rc1
Summary: Beast
Author-email: jqssun <jqssun+git@googlemail.com>
Project-URL: Homepage, https://github.com/jqssun/bestie
Project-URL: Repository, https://github.com/jqssun/bestie.git
